godzillamididataset/HaystackSearch.py
godzillamididataset/MIDI.py
godzillamididataset/README.md
godzillamididataset/SyllablesSearch.py
godzillamididataset/TCUPY.py
godzillamididataset/TMELODIES.py
godzillamididataset/TMIDIX.py
godzillamididataset/TPLOTS.py
godzillamididataset/__init__.py
godzillamididataset/directory_tree.py
godzillamididataset/fast_parallel_extract.py
godzillamididataset/midi_to_colab_audio.py
godzillamididataset/sample_midis.py
godzillamididataset/search_and_filter.py
godzillamididataset/x_transformer_2_3_1.py
godzillamididataset/artwork/Godzilla-MIDI-Dataset.png
godzillamididataset/artwork/Project-Los-Angeles.png
godzillamididataset/artwork/README.md
godzillamididataset/artwork/Tegridy-Code-2025.png
godzillamididataset/artwork/__init__.py
godzillamididataset/examples/README.md
godzillamididataset/examples/__init__.py
godzillamididataset/midi_samples/__init__.py
godzillamididataset/seed_midis/Godzilla-MIDI-Dataset-MI-Seed-1.mid
godzillamididataset/seed_midis/Godzilla-MIDI-Dataset-MI-Seed-2.mid
godzillamididataset/seed_midis/Godzilla-MIDI-Dataset-MI-Seed-3.mid
godzillamididataset/seed_midis/Godzilla-MIDI-Dataset-MI-Seed-4.mid
godzillamididataset/seed_midis/Godzilla-MIDI-Dataset-MI-Seed-5.mid
godzillamididataset/seed_midis/Godzilla-MIDI-Dataset-MI-Seed-6.mid
godzillamididataset/seed_midis/Godzilla-MIDI-Dataset-Piano-Seed-1.mid
godzillamididataset/seed_midis/Godzilla-MIDI-Dataset-Piano-Seed-2.mid
godzillamididataset/seed_midis/Godzilla-MIDI-Dataset-Piano-Seed-3.mid
godzillamididataset/seed_midis/Godzilla-MIDI-Dataset-Piano-Seed-4.mid
godzillamididataset/seed_midis/Godzilla-MIDI-Dataset-Piano-Seed-5.mid
godzillamididataset/seed_midis/Godzilla-MIDI-Dataset-Piano-Seed-6.mid
godzillamididataset/seed_midis/README.md
godzillamididataset/seed_midis/__init__.py
godzillamididataset-25.6.5.dist-info/licenses/LICENSE
godzillamididataset-25.6.5.dist-info/METADATA
godzillamididataset-25.6.5.dist-info/WHEEL
godzillamididataset-25.6.5.dist-info/top_level.txt
godzillamididataset-25.6.5.dist-info/RECORD
